[{"games":[{"id":1,"name":"John","rounds":[{"idRound":1,"score":7}]},{"id":2,"name":"Daniel","rounds":[{"idRound":1,"score":2}]},{"id":3,"name":"Thomas","rounds":[{"idRound":1,"score":2}]},{"id":4,"name":"King","rounds":[{"idRound":1,"score":9}]}]},{"rounds":[{"id":1,"scorePlayer1":10,"scorePlayer2":20,"scorePlayer3":30,"scorePlayer4":41},{"id":2,"scorePlayer1":10,"scorePlayer2":20,"scorePlayer3":30,"scorePlayer4":42},{"id":3,"scorePlayer1":10,"scorePlayer2":20,"scorePlayer3":30,"scorePlayer4":32},{"id":0.3779847086952035,"scorePlayer1":0,"scorePlayer2":0,"scorePlayer3":0,"scorePlayer4":0}]}]